paginator/__init__.py
paginator/page.py
django_paginator2-1.1.3.dist-info/METADATA
django_paginator2-1.1.3.dist-info/WHEEL
django_paginator2-1.1.3.dist-info/top_level.txt
django_paginator2-1.1.3.dist-info/RECORD
